drinkingbird/__init__.py
drinkingbird/actions.py
drinkingbird/art.py
drinkingbird/base.py
drinkingbird/cli.py
drinkingbird-0.2.1.dist-info/LICENSE.txt
drinkingbird-0.2.1.dist-info/METADATA
drinkingbird-0.2.1.dist-info/WHEEL
drinkingbird-0.2.1.dist-info/entry_points.txt
drinkingbird-0.2.1.dist-info/top_level.txt
drinkingbird-0.2.1.dist-info/RECORD
