Metadata-Version: 2.1
Name: drinkingbird
Version: 0.2.1
Summary: Program to keep your browser/computer active
Home-page: https://github.com/Dih5/drinkingbird
Author: Dih5
Author-email: dihedralfive@gmail.com
License: UNKNOWN
Platform: UNKNOWN
Classifier: Development Status :: 4 - Beta
Classifier: Intended Audience :: End Users/Desktop
Classifier: License :: OSI Approved :: MIT License
Classifier: Natural Language :: English
Classifier: Programming Language :: Python :: 3
Classifier: Programming Language :: Python :: 3.5
Classifier: Programming Language :: Python :: 3.6
Classifier: Programming Language :: Python :: 3.7
Classifier: Programming Language :: Python :: 3.8
Classifier: Programming Language :: Python :: 3.9
Classifier: Programming Language :: Python :: 3.10
License-File: LICENSE.txt
Requires-Dist: pynput
Requires-Dist: click
Provides-Extra: docs
Requires-Dist: nbsphinx ; extra == 'docs'
Requires-Dist: sphinx-rtd-theme ; extra == 'docs'
Requires-Dist: IPython ; extra == 'docs'
Provides-Extra: test
Requires-Dist: pytest ; extra == 'test'
